pyiso3166/__init__.py
pyiso3166/pyiso3166.py
pyiso3166-0.0.3.dist-info/AUTHORS
pyiso3166-0.0.3.dist-info/LICENSE
pyiso3166-0.0.3.dist-info/METADATA
pyiso3166-0.0.3.dist-info/WHEEL
pyiso3166-0.0.3.dist-info/top_level.txt
pyiso3166-0.0.3.dist-info/RECORD
